LICENSE
MANIFEST.in
README.md
setup.cfg
setup.py
restring/__init__.py
restring/gears.py
restring/guigears.py
restring/restring.py
restring/settings.py
restring.egg-info/PKG-INFO
restring.egg-info/SOURCES.txt
restring.egg-info/dependency_links.txt
restring.egg-info/entry_points.txt
restring.egg-info/requires.txt
restring.egg-info/top_level.txt
restring/imgs/credits.png
restring/imgs/restring_banner_vanilla.png
restring/imgs/restring_banner_writings.png