Metadata-Version: 2.1
Name: restring
Version: 0.1.20
Summary: Functional enrichment terms aggregator.
Home-page: https://github.com/Stemanz/restring
Download-URL: https://github.com/Stemanz/restring/archive/master.zip
Author: Stefano Manzini
Author-email: stefano.manzini@gmail.com
License: GPL-3.0
Keywords: String,functional enrichment,GO,David,KEGG,pathways
Requires-Python: >3.8.0
License-File: LICENSE
